PyYADL/__init__.py
PyYADL/distributed_lock.py
PyYADL/redis_lock.py
PyYADL/tests/__init__.py
PyYADL/tests/test_redis_lock.py
PyYADL-1.0.0.dist-info/DESCRIPTION.rst
PyYADL-1.0.0.dist-info/METADATA
PyYADL-1.0.0.dist-info/RECORD
PyYADL-1.0.0.dist-info/WHEEL
PyYADL-1.0.0.dist-info/metadata.json
PyYADL-1.0.0.dist-info/top_level.txt
