Metadata-Version: 2.0
Name: PyYADL
Version: 1.0.0
Summary: Yet another distributed lock for python
Home-page: https://github.com/PawelJ-PL/PyYADL
Author: Pawel
Author-email: inne.poczta@gmail.com
License: MIT
Keywords: distributed lock Redis implementation
Platform: UNKNOWN
Classifier: Development Status :: 5 - Production/Stable
Classifier: Intended Audience :: Developers
Classifier: License :: OSI Approved :: MIT License
Classifier: Programming Language :: Python :: 3 :: Only
Classifier: Topic :: Software Development :: Libraries
Requires-Python: >=3
Requires-Dist: redis
Provides-Extra: test
Requires-Dist: coverage; extra == 'test'
Requires-Dist: flake8; extra == 'test'
Requires-Dist: nose; extra == 'test'
